unicom/__init__.py
unicom/_version.py
unicom/apps.py
unicom/signals.py
unicom/urls.py
unicom/admin/__init__.py
unicom/admin/account_admin.py
unicom/admin/channel_admin.py
unicom/admin/chat_admin.py
unicom/admin/draft_message_admin.py
unicom/admin/email_inline_image_admin.py
unicom/admin/filters.py
unicom/admin/member_admin.py
unicom/admin/message_admin.py
unicom/admin/message_template_admin.py
unicom/admin/request_admin.py
unicom/management/__init__.py
unicom/management/commands/__init__.py
unicom/management/commands/mail_inbox_listen.py
unicom/management/commands/run_as_llm_chat.py
unicom/management/commands/send_scheduled_messages.py
unicom/management/commands/start_imap_listeners.py
unicom/migrations/0001_initial.py
unicom/migrations/0002_emailinlineimage.py
unicom/migrations/0003_alter_emailinlineimage_email_message.py
unicom/migrations/0004_messagetemplateinlineimage.py
unicom/migrations/0005_emailinlineimage_hash_and_more.py
unicom/migrations/0006_channel_created_at_channel_created_by_and_more.py
unicom/migrations/0007_message_imap_uid.py
unicom/migrations/0008_add_all_members_group.py
unicom/migrations/0009_add_tool_call_types.py
unicom/migrations/0010_request_initial_request_request_llm_calls_count_and_more.py
unicom/migrations/0011_toolcall_add_message_reference.py
unicom/migrations/0012_message_response_to_tool_call_and_more.py
unicom/migrations/__init__.py
unicom/models/__init__.py
unicom/models/account.py
unicom/models/account_chat.py
unicom/models/channel.py
unicom/models/chat.py
unicom/models/constants.py
unicom/models/draft_message.py
unicom/models/fields.py
unicom/models/member.py
unicom/models/member_group.py
unicom/models/message.py
unicom/models/message_template.py
unicom/models/request.py
unicom/models/request_category.py
unicom/models/tool_call.py
unicom/models/update.py
unicom/services/__init__.py
unicom/services/chat_summary.py
unicom/services/decode_base64_image.py
unicom/services/get_public_origin.py
unicom/services/html_inline_images.py
django_unicom-2025.9.28.141145.dist-info/METADATA
django_unicom-2025.9.28.141145.dist-info/WHEEL
django_unicom-2025.9.28.141145.dist-info/top_level.txt
django_unicom-2025.9.28.141145.dist-info/RECORD
