Metadata-Version: 2.4
Name: django-unicom
Version: 2025.9.28.141145
Summary: Unified communication layer for Django (Telegram, WhatsApp, Email)
Home-page: https://github.com/meena-erian/unicom
Author: Meena (Menas) Erian
Author-email: hi@menas.pro
Classifier: Framework :: Django
Classifier: Programming Language :: Python :: 3
Classifier: License :: OSI Approved :: MIT License
Requires-Dist: Django<5.0,>=3.2
Requires-Dist: psycopg2-binary<3.0,>=2.9
Requires-Dist: urllib3<3.0,>=2.4.0
Requires-Dist: dnspython<3.0,>=2.7.0
Requires-Dist: authheaders>=0.15.0
Requires-Dist: pyspf>=2.0.0
Requires-Dist: dkimpy>=1.1.0
Requires-Dist: requests<3.0,>=2.31.0
Requires-Dist: IMAPClient>=3.0.1
Requires-Dist: dnspython<3.0,>=2.7.0
Requires-Dist: Pillow>=10.4.0
Requires-Dist: django-ace>=1.39.2
Requires-Dist: fa2svg==0.1.9
Requires-Dist: pytz>=2024.1
Requires-Dist: openai
Requires-Dist: pydub>=0.25.1
Requires-Dist: WeasyPrint==52.5
Requires-Dist: playwright<2.0,>=1.45.0
Provides-Extra: dev
Requires-Dist: pytest<9.0,>=8.3.5; extra == "dev"
Requires-Dist: pytest-django<5.0,>=4.11.1; extra == "dev"
Requires-Dist: charset-normalizer<4.0,>=3.1.0; extra == "dev"
Requires-Dist: python-dotenv<2.0,>=1.0; extra == "dev"
Dynamic: author
Dynamic: author-email
Dynamic: classifier
Dynamic: description
Dynamic: description-content-type
Dynamic: home-page
Dynamic: provides-extra
Dynamic: requires-dist
Dynamic: summary
